halmoney/__init__.py
halmoney/anydb.py
halmoney/basic_data.py
halmoney/ganada.py
halmoney/jfinder.py
halmoney/mail.py
halmoney/mailmail.py
halmoney/pcell.py
halmoney/pcell_event.py
halmoney/pyclick.py
halmoney/pynal.py
halmoney/scolor.py
halmoney/word.py
halmoney/youtil.py
halmoney-3.0.0.dist-info/METADATA
halmoney-3.0.0.dist-info/WHEEL
halmoney-3.0.0.dist-info/top_level.txt
halmoney-3.0.0.dist-info/RECORD
