Metadata-Version: 2.1
Name: halmoney
Version: 3.0.0
Summary: Easy Read / Write for Excel, Word, Color, Etc using Python
Home-page: https://github.com/sjpark/halmoney
Download-URL: https://github.com/sjpark/halmoney/archive/v3.0.0.tar.gz
Author: sjpark
Author-email: sjpkorea@yahoo.com
Classifier: License :: OSI Approved :: MIT License
Requires-Python: >=3.5
